CHANGELOG.rst
LICENSE
MANIFEST.in
Makefile
README.rst
requirements.txt
setup.py
test-requirements.txt
tox.ini
src/vmshepherd_aws_drivers/__init__.py
src/vmshepherd_aws_drivers/aws_iaas_driver.py
src/vmshepherd_aws_drivers/aws_preset_driver.py
src/vmshepherd_aws_drivers.egg-info/PKG-INFO
src/vmshepherd_aws_drivers.egg-info/SOURCES.txt
src/vmshepherd_aws_drivers.egg-info/dependency_links.txt
src/vmshepherd_aws_drivers.egg-info/entry_points.txt
src/vmshepherd_aws_drivers.egg-info/not-zip-safe
src/vmshepherd_aws_drivers.egg-info/requires.txt
src/vmshepherd_aws_drivers.egg-info/top_level.txt
tests/__init__.py
tests/unit/__init__.py
tests/unit/common.py
tests/unit/test_aws_iaas_driver.py
tests/unit/test_aws_preset_driver.py