Metadata-Version: 1.1
Name: vmshepherd-aws-drivers
Version: 1.3.1
Summary: AWS drivers for VmShepherd
Home-page: https://github.com/Dreamlab/vmshepherd-aws-drivers
Author: Dreamlab - PaaS KRK
Author-email: paas-support@dreamlab.pl
License: UNKNOWN
Keywords: vmshepherd,AWS,ASG
Platform: UNKNOWN
Classifier: Programming Language :: Python :: 3.6
Classifier: Programming Language :: Python :: 3.7
Classifier: Operating System :: POSIX
